<annotation>
	<folder>images</folder>
	<filename>mixed (389).jpg</filename>
	<path>C:\Users\Merida\Desktop\Multi Class Vehicle\images\mixed (389).jpg</path>
	<source>
		<database>Unknown</database>
	</source>
	<size>
		<width>4608</width>
		<height>2592</height>
		<depth>3</depth>
	</size>
	<segmented>0</segmented>
	<object>
		<name>van</name>
		<pose>Unspecified</pose>
		<truncated>0</truncated>
		<difficult>0</difficult>
		<bndbox>
			<xmin>1599</xmin>
			<ymin>1393</ymin>
			<xmax>2954</xmax>
			<ymax>2583</ymax>
		</bndbox>
	</object>
	<object>
		<name>van</name>
		<pose>Unspecified</pose>
		<truncated>0</truncated>
		<difficult>0</difficult>
		<bndbox>
			<xmin>2639</xmin>
			<ymin>1268</ymin>
			<xmax>3294</xmax>
			<ymax>1828</ymax>
		</bndbox>
	</object>
	<object>
		<name>van</name>
		<pose>Unspecified</pose>
		<truncated>0</truncated>
		<difficult>0</difficult>
		<bndbox>
			<xmin>3249</xmin>
			<ymin>1208</ymin>
			<xmax>3389</xmax>
			<ymax>1573</ymax>
		</bndbox>
	</object>
	<object>
		<name>rickshaw</name>
		<pose>Unspecified</pose>
		<truncated>0</truncated>
		<difficult>0</difficult>
		<bndbox>
			<xmin>1359</xmin>
			<ymin>1088</ymin>
			<xmax>1664</xmax>
			<ymax>1383</ymax>
		</bndbox>
	</object>
	<object>
		<name>rickshaw</name>
		<pose>Unspecified</pose>
		<truncated>0</truncated>
		<difficult>0</difficult>
		<bndbox>
			<xmin>1774</xmin>
			<ymin>1058</ymin>
			<xmax>1974</xmax>
			<ymax>1388</ymax>
		</bndbox>
	</object>
	<object>
		<name>car</name>
		<pose>Unspecified</pose>
		<truncated>0</truncated>
		<difficult>0</difficult>
		<bndbox>
			<xmin>1589</xmin>
			<ymin>1123</ymin>
			<xmax>1804</xmax>
			<ymax>1338</ymax>
		</bndbox>
	</object>
	<object>
		<name>car</name>
		<pose>Unspecified</pose>
		<truncated>0</truncated>
		<difficult>0</difficult>
		<bndbox>
			<xmin>1234</xmin>
			<ymin>1158</ymin>
			<xmax>1384</xmax>
			<ymax>1313</ymax>
		</bndbox>
	</object>
	<object>
		<name>rickshaw</name>
		<pose>Unspecified</pose>
		<truncated>0</truncated>
		<difficult>0</difficult>
		<bndbox>
			<xmin>3459</xmin>
			<ymin>1023</ymin>
			<xmax>3564</xmax>
			<ymax>1178</ymax>
		</bndbox>
	</object>
</annotation>
