<annotation>
	<folder>images</folder>
	<filename>launch (266).jpg</filename>
	<path>C:\Users\Merida\Desktop\Launch\images\launch (266).jpg</path>
	<source>
		<database>Unknown</database>
	</source>
	<size>
		<width>960</width>
		<height>720</height>
		<depth>3</depth>
	</size>
	<segmented>0</segmented>
	<object>
		<name>boat</name>
		<pose>Unspecified</pose>
		<truncated>0</truncated>
		<difficult>0</difficult>
		<bndbox>
			<xmin>796</xmin>
			<ymin>539</ymin>
			<xmax>950</xmax>
			<ymax>614</ymax>
		</bndbox>
	</object>
	<object>
		<name>launch</name>
		<pose>Unspecified</pose>
		<truncated>0</truncated>
		<difficult>0</difficult>
		<bndbox>
			<xmin>848</xmin>
			<ymin>383</ymin>
			<xmax>957</xmax>
			<ymax>509</ymax>
		</bndbox>
	</object>
	<object>
		<name>launch</name>
		<pose>Unspecified</pose>
		<truncated>0</truncated>
		<difficult>0</difficult>
		<bndbox>
			<xmin>63</xmin>
			<ymin>99</ymin>
			<xmax>862</xmax>
			<ymax>607</ymax>
		</bndbox>
	</object>
	<object>
		<name>boat</name>
		<pose>Unspecified</pose>
		<truncated>1</truncated>
		<difficult>0</difficult>
		<bndbox>
			<xmin>366</xmin>
			<ymin>677</ymin>
			<xmax>879</xmax>
			<ymax>720</ymax>
		</bndbox>
	</object>
</annotation>
