<annotation>
	<folder>images</folder>
	<filename>launch (309).jpg</filename>
	<path>C:\Users\Merida\Desktop\Launch\images\launch (309).jpg</path>
	<source>
		<database>Unknown</database>
	</source>
	<size>
		<width>960</width>
		<height>720</height>
		<depth>3</depth>
	</size>
	<segmented>0</segmented>
	<object>
		<name>launch</name>
		<pose>Unspecified</pose>
		<truncated>1</truncated>
		<difficult>0</difficult>
		<bndbox>
			<xmin>604</xmin>
			<ymin>233</ymin>
			<xmax>960</xmax>
			<ymax>378</ymax>
		</bndbox>
	</object>
	<object>
		<name>launch</name>
		<pose>Unspecified</pose>
		<truncated>1</truncated>
		<difficult>0</difficult>
		<bndbox>
			<xmin>1</xmin>
			<ymin>253</ymin>
			<xmax>603</xmax>
			<ymax>349</ymax>
		</bndbox>
	</object>
	<object>
		<name>launch</name>
		<pose>Unspecified</pose>
		<truncated>1</truncated>
		<difficult>0</difficult>
		<bndbox>
			<xmin>6</xmin>
			<ymin>365</ymin>
			<xmax>960</xmax>
			<ymax>581</ymax>
		</bndbox>
	</object>
	<object>
		<name>launch</name>
		<pose>Unspecified</pose>
		<truncated>1</truncated>
		<difficult>0</difficult>
		<bndbox>
			<xmin>9</xmin>
			<ymin>557</ymin>
			<xmax>861</xmax>
			<ymax>720</ymax>
		</bndbox>
	</object>
</annotation>
